LICENSE
MANIFEST.in
README.md
setup.py
django_markdocs.egg-info/PKG-INFO
django_markdocs.egg-info/SOURCES.txt
django_markdocs.egg-info/dependency_links.txt
django_markdocs.egg-info/requires.txt
django_markdocs.egg-info/top_level.txt
markdocs/__init__.py
markdocs/admin.py
markdocs/apps.py
markdocs/conf.py
markdocs/models.py
markdocs/tests.py
markdocs/urls.py
markdocs/util.py
markdocs/views.py
markdocs/__pycache__/__init__.cpython-36.pyc
markdocs/__pycache__/admin.cpython-36.pyc
markdocs/__pycache__/conf.cpython-36.pyc
markdocs/__pycache__/models.cpython-36.pyc
markdocs/__pycache__/urls.cpython-36.pyc
markdocs/__pycache__/util.cpython-36.pyc
markdocs/__pycache__/views.cpython-36.pyc
markdocs/mdocs/index.md
markdocs/migrations/__init__.py
markdocs/migrations/__pycache__/__init__.cpython-36.pyc
markdocs/templates/markdocs/md_content.html
markdocs/templates/markdocs/md_index.html