Metadata-Version: 1.1
Name: django-markdocs
Version: 1.0.2
Summary: Generate static HTML pages from .md files.
Home-page: https://github.com/aaronmarkey/django-markdocs
Author: Aaron Markey
Author-email: markeyaaron@gmail.com
License: MIT License 
Platform: UNKNOWN
Classifier: Environment :: Web Environment
Classifier: Framework :: Django
Classifier: Framework :: Django :: 2.0
Classifier: Intended Audience :: Developers
Classifier: License :: OSI Approved :: MIT License
Classifier: Operating System :: OS Independent
Classifier: Programming Language :: Python
Classifier: Programming Language :: Python :: 3
Classifier: Topic :: Internet :: WWW/HTTP
